dantro/__init__.py
dantro/_copy.py
dantro/_dag_utils.py
dantro/_hash.py
dantro/_import_tools.py
dantro/_registry.py
dantro/_yaml.py
dantro/abc.py
dantro/base.py
dantro/dag.py
dantro/data_mngr.py
dantro/exceptions.py
dantro/logging.py
dantro/plot_mngr.py
dantro/tools.py
dantro/cfg/base_plots.yml
dantro/containers/__init__.py
dantro/containers/_registry.py
dantro/containers/general.py
dantro/containers/link.py
dantro/containers/numeric.py
dantro/containers/path.py
dantro/containers/xr.py
dantro/data_loaders/__init__.py
dantro/data_loaders/_registry.py
dantro/data_loaders/fspath.py
dantro/data_loaders/hdf5.py
dantro/data_loaders/numpy.py
dantro/data_loaders/pandas.py
dantro/data_loaders/pickle.py
dantro/data_loaders/text.py
dantro/data_loaders/xarray.py
dantro/data_loaders/yaml.py
dantro/data_ops/__init__.py
dantro/data_ops/_base_ops.py
dantro/data_ops/apply.py
dantro/data_ops/arr_ops.py
dantro/data_ops/ctrl_ops.py
dantro/data_ops/db.py
dantro/data_ops/db_tools.py
dantro/data_ops/expr_ops.py
dantro/data_ops/hooks.py
dantro/groups/__init__.py
dantro/groups/_registry.py
dantro/groups/dirpath.py
dantro/groups/graph.py
dantro/groups/labelled.py
dantro/groups/ordered.py
dantro/groups/psp.py
dantro/groups/time_series.py
dantro/mixins/__init__.py
dantro/mixins/base.py
dantro/mixins/general.py
dantro/mixins/indexing.py
dantro/mixins/numeric.py
dantro/mixins/proxy_support.py
dantro/plot/__init__.py
dantro/plot/_cfg.py
dantro/plot/plot_helper.py
dantro/plot/creators/__init__.py
dantro/plot/creators/base.py
dantro/plot/creators/psp.py
dantro/plot/creators/pyplot.py
dantro/plot/funcs/__init__.py
dantro/plot/funcs/_multiplot.py
dantro/plot/funcs/_utils.py
dantro/plot/funcs/basic.py
dantro/plot/funcs/generic.py
dantro/plot/funcs/graph.py
dantro/plot/funcs/multiplot.py
dantro/plot/funcs/snsplot.py
dantro/plot/utils/__init__.py
dantro/plot/utils/_file_writer.py
dantro/plot/utils/color_mngr.py
dantro/plot/utils/mpl.py
dantro/plot/utils/plot_func.py
dantro/proxy/__init__.py
dantro-0.21.2.dist-info/licenses/COPYING
dantro-0.21.2.dist-info/licenses/COPYING.LESSER
dantro-0.21.2.dist-info/METADATA
dantro-0.21.2.dist-info/WHEEL
dantro-0.21.2.dist-info/top_level.txt
dantro-0.21.2.dist-info/RECORD
