Metadata-Version: 2.4
Name: dantro
Version: 0.21.2
Summary: Handle, transform, and visualize hierarchically structured data
Home-page: https://gitlab.com/utopia-project/dantro
Author: dantro developers
Author-email: dantro-dev@iup.uni.heidelberg.de
License: LGPL-3.0-or-later
Classifier: Intended Audience :: Science/Research
Classifier: Programming Language :: Python :: 3.9
Classifier: Programming Language :: Python :: 3.10
Classifier: Programming Language :: Python :: 3.11
Classifier: Programming Language :: Python :: 3.12
Classifier: Programming Language :: Python :: 3.13
Classifier: Programming Language :: Python :: 3.14
Classifier: Operating System :: Microsoft :: Windows
Classifier: Operating System :: MacOS
Classifier: Operating System :: Unix
Classifier: Operating System :: POSIX :: Linux
Classifier: Topic :: Utilities
Classifier: License :: OSI Approved :: GNU Lesser General Public License v3 or later (LGPLv3+)
Requires-Python: >=3.9
License-File: COPYING
License-File: COPYING.LESSER
Requires-Dist: numpy
Requires-Dist: scipy
Requires-Dist: xarray
Requires-Dist: sympy
Requires-Dist: dask
Requires-Dist: toolz
Requires-Dist: distributed
Requires-Dist: h5py
Requires-Dist: h5netcdf
Requires-Dist: matplotlib
Requires-Dist: seaborn
Requires-Dist: networkx
Requires-Dist: ruamel.yaml
Requires-Dist: dill
Requires-Dist: yayaml>=0.2
Requires-Dist: paramspace
Provides-Extra: test
Requires-Dist: pytest; extra == "test"
Requires-Dist: pytest-cov; extra == "test"
Requires-Dist: tox; extra == "test"
Requires-Dist: pre-commit; extra == "test"
Requires-Dist: pooch; extra == "test"
Requires-Dist: cftime; extra == "test"
Provides-Extra: doc
Requires-Dist: sphinx>=5; extra == "doc"
Requires-Dist: sphinx-book-theme; extra == "doc"
Requires-Dist: sphinx-togglebutton; extra == "doc"
Requires-Dist: ipython; extra == "doc"
Requires-Dist: pickleshare; extra == "doc"
Provides-Extra: dev
Requires-Dist: pytest; extra == "dev"
Requires-Dist: pytest-cov; extra == "dev"
Requires-Dist: tox; extra == "dev"
Requires-Dist: pre-commit; extra == "dev"
Requires-Dist: pooch; extra == "dev"
Requires-Dist: cftime; extra == "dev"
Requires-Dist: sphinx>=5; extra == "dev"
Requires-Dist: sphinx-book-theme; extra == "dev"
Requires-Dist: sphinx-togglebutton; extra == "dev"
Requires-Dist: ipython; extra == "dev"
Requires-Dist: pickleshare; extra == "dev"
Dynamic: author
Dynamic: author-email
Dynamic: classifier
Dynamic: description
Dynamic: home-page
Dynamic: license
Dynamic: license-file
Dynamic: provides-extra
Dynamic: requires-dist
Dynamic: requires-python
Dynamic: summary
